Workbook
Name MemberNames: 'MEMBER REGISTER (ಸದಸ್ಯರ ಪಟ್ಟಿ)'!$B$5:$B$22

Sheet Dashboard Item (ಡ್ಯಾಶ್‌ಬೋರ್ಡ್ ಅ
A1: CHIT FUND DASHBOARD (ಚಿಟ್ ಫಂಡ್ ಡ್ಯಾಶ್‌ಬೋರ್ಡ್)
A2: Ongoing chit fund (ನಡೆಯುತ್ತಿರುವ ಚಿಟ್ ಫಂಡ್) | 18 members (ಸದಸ್ಯರು) | ₹500 monthly contribution per member (ಪ್ರತಿ ಸದಸ್ಯರ ಮಾಸಿಕ ಕೊಡುಗೆ) | Auction / bidding (ಹರಾಜು / ಬಿಡ್ಡಿಂಗ್)
A4: Dashboard Item (ಡ್ಯಾಶ್‌ಬೋರ್ಡ್ ಅಂಶ) | B4: Value (ಮೌಲ್ಯ)
A5: Members (ಸದಸ್ಯರು) | B5: =COUNTA('MEMBER REGISTER (ಸದಸ್ಯರ ಪಟ್ಟಿ)'!B5:B22) -> 18
A6: Monthly contribution per member (ಪ್ರತಿ ಸದಸ್ಯರ ಮಾಸಿಕ ಕೊಡುಗೆ) | B6: =IFERROR(INDEX('MEMBER REGISTER (ಸದಸ್ಯರ ಪಟ್ಟಿ)'!C5:C500,MATCH("Bharath (ಭರತ್)",'MEMBER REGISTER (ಸದಸ್ಯರ ಪಟ್ಟಿ)'!B5:B500,0)),500) -> 500
A7: Expected monthly collection (ನಿರೀಕ್ಷಿತ ಮಾಸಿಕ ಸಂಗ್ರಹ) | B7: =SUMPRODUCT(('MEMBER REGISTER (ಸದಸ್ಯರ ಪಟ್ಟಿ)'!D5:D500="Yes")*('MEMBER REGISTER (ಸದಸ್ಯರ ಪಟ್ಟಿ)'!C5:C500)) -> 9000
A8: Total Account Balance (ಒಟ್ಟು ಖಾತೆ ಬಾಕಿ) | B8: =SUM('MEMBER PAYMENT LEDGER (ಸದಸ್ಯರ ಪ'!D5:D997)+SUM('RECEIVED AMOUNT ( ಸ್ವೀಕರಿಸಿದ ಮೊ'!C5:C1003)-SUM('CHIT REGISTER (ಮಾಸಿಕ ಚಿಟ್ ನೋಂದಣ'!C5:C502) -> 1000
A9: Total Amount Needs to Recover (ವಸೂಲಿ ಮಾಡಬೇಕಾದ ಒಟ್ಟು ಮೊತ್ತ) | B9: =MAX(0,SUM('CHIT REGISTER (ಮಾಸಿಕ ಚಿಟ್ ನೋಂದಣ'!$D$5:$D$502)-SUMIFS('MEMBER PAYMENT LEDGER (ಸದಸ್ಯರ ಪ'!$D$5:$D$997,'MEMBER PAYMENT LEDGER (ಸದಸ್ಯರ ಪ'!$F$5:$F$997,"PAID")) -> 9700

Sheet MEMBER REGISTER (ಸದಸ್ಯರ ಪಟ್ಟಿ)
A1: MEMBER REGISTER (ಸದಸ್ಯರ ಪಟ್ಟಿ)
A2: Maintain the 18 group members here (ಇಲ್ಲಿ 18 ಸದಸ್ಯರ ವಿವರಗಳನ್ನು ನಿರ್ವಹಿಸಿ)
A4: Member ID (ಸದಸ್ಯರ ಐಡಿ) | B4: Member Name (ಸದಸ್ಯರ ಹೆಸರು) | C4: Monthly Contribution (₹) (ಮಾಸಿಕ ಕೊಡುಗೆ) | D4: Active? (ಸಕ್ರಿಯವೇ?)
A5: M001 | B5: Bharath (ಭರತ್) | C5: 500 | D5: Yes
A6: M002 | B6: Manjunath LN (Bangalore) (ಮಂಜುನಾಥ್ ಎಲ್‌ಎನ್ (ಬೆಂಗಳೂರು)) | C6: 500 | D6: Yes
A7: M003 | B7: Jayanna (ಜಯಣ್ಣ) | C7: 500 | D7: Yes
A8: M004 | B8: Jayanth (ಜಯಂತ್) | C8: 500 | D8: Yes
A9: M005 | B9: Vijay (ವಿಜಯ್) | C9: 500 | D9: Yes
A10: M006 | B10: Kumar LR (ಕುಮಾರ್ ಎಲ್‌ಆರ್) | C10: 500 | D10: Yes
A11: M007 | B11: Kiran (ಕಿರಣ್) | C11: 500 | D11: Yes
A12: M008 | B12: Charan (ಚರಣ್) | C12: 500 | D12: Yes
A13: M009 | B13: Manjunath CM (ಮಂಜುನಾಥ್ ಸಿ ಎಂ) | C13: 500 | D13: Yes
A14: M010 | B14: Yogesh (ಯೋಗೇಶ್) | C14: 500 | D14: Yes
A15: M011 | B15: Sampath (ಸಂಪತ್) | C15: 500 | D15: Yes
A16: M012 | B16: Manjunath LC (ಮಂಜುನಾಥ್ ಎಲ್ ಸಿ) | C16: 500 | D16: Yes
... A22: M018 | B22: Sanju (ಸಂಜು) | C22: 500 | D22: Yes

Sheet RECEIVED AMOUNT ( ಸ್ವೀಕರಿಸಿದ ಮೊ
A1: MONTHLY CHIT RECEIVED AMOUNT ಮಾಸಿಕ ಚೀಟಿ ಸ್ವೀಕರಿಸಿದ ಮೊತ್ತ)
A2: Record actual Payment received from chit Members These receipts are included in Total Account Balance. (ಚಿಟ್ ಪಡೆದವರಿಂದ ಸೇರಿ ನಿಜವಾಗಿ ಬಂದ ಪಾವತಿಯನ್ನು ದಾಖಲಿಸಿ. ಈ ಮೊತ್ತ ಖಾತೆಯ ಒಟ್ಟು ಬಾಕಿಗೆ ಸೇರುತ್ತದೆ.)
A4: SL No (ಕ್ರಮ ಸಂಖ್ಯೆ) | B4: Date (ದಿನಾಂಕ) | C4: Received Amount (₹) (ಸ್ವೀಕರಿಸಿದ ಮೊತ್ತ) | D4: Member Name (ಸದಸ್ಯರ ಹೆಸರು) | E4: Notes (ಟಿಪ್ಪಣಿಗಳು)
A5: 1 | B5: 46307 | C5: 10000 | D5: ALL
A6: =IF(B6="","",ROW()-4)
A7: =IF(B7="","",ROW()-4)
A8: =IF(B8="","",ROW()-4)
A9: =IF(B9="","",ROW()-4)
A10: =IF(B10="","",ROW()-4)
A11: =IF(B11="","",ROW()-4)
A12: =IF(B12="","",ROW()-4)
A13: =IF(B13="","",ROW()-4)
A14: =IF(B14="","",ROW()-4)
A15: =IF(B15="","",ROW()-4)
A16: =IF(B16="","",ROW()-4)
A17: =IF(B17="","",ROW()-4)
... A1003: =IF(B1003="","",ROW()-4)

Sheet CHIT REGISTER (ಮಾಸಿಕ ಚಿಟ್ ನೋಂದಣ
A1: CHIT REGISTER (ಮಾಸಿಕ ಚಿಟ್ ನೋಂದಣಿ)
A2: Add one row per chit month (ಪ್ರತಿ ತಿಂಗಳ ಚಿಟ್‌ಗೆ ಒಂದು ಸಾಲು ಸೇರಿಸಿ). Enter actual payouts and the amount the Members must repay (ಸದಸ್ಯರು ಪಾವತಿಸಿದ ಮೊತ್ತ ಮತ್ತು ಅವರು ಮರುಪಾವತಿಸಬೇಕಾದ ಮೊತ್ತ ನಮೂದಿಸಿ); unpaid amounts are not counted as cash in the dashboard (ಪಾವತಿಯಾಗದ ಮೊತ್ತವನ್ನು ಖಾತೆ ನಗದು ಎಂದು ಪರಿಗಣಿಸಲಾಗುವುದಿಲ್ಲ).
A4: SL No (ಕ್ರಮ ಸಂಖ್ಯೆ) | B4: Date (ದಿನಾಂಕ) | C4: Total Amount Taken (₹) (ಪಡೆದ ಒಟ್ಟು ಮೊತ್ತ) | D4: Total Amount Taken with Interest (₹) (ಬಡ್ಡಿಯೊಂದಿಗೆ ಒಟ್ಟು ಮೊತ್ತ) | E4: Amount Needs to be Paid Next Month (₹) (ಮುಂದಿನ ತಿಂಗಳು ಪಾವತಿಸಬೇಕಾದ ಮೊತ್ತ) | F4: Member Name (ಸದಸ್ಯರ ಹೆಸರು) | G4: Payment Status (ಪಾವತಿ ಸ್ಥಿತಿ) | H4: Notes (ಟಿಪ್ಪಣಿಗಳು)
A5: 1 | B5: 46307 | C5: 5000 | D5: 5400 | E5: 5400 | F5: Siddha(Shiva) (ಸಿದ್ದ (ಶಿವ)) | G5: =IF(B5="","","UNPAID") -> UNPAID
A6: 2 | B6: 46307 | C6: 4000 | D6: 4300 | E6: 4300 | F6: Charan (ಚರಣ್) | G6: =IF(B6="","","UNPAID") -> UNPAID
A7: =IF(B7="","",ROW()-4) | G7: =IF(B7="","","UNPAID")
A8: =IF(B8="","",ROW()-4) | G8: =IF(B8="","","UNPAID")
A9: =IF(B9="","",ROW()-4) | G9: =IF(B9="","","UNPAID")
A10: =IF(B10="","",ROW()-4) | G10: =IF(B10="","","UNPAID")
A11: =IF(B11="","",ROW()-4) | G11: =IF(B11="","","UNPAID")
A12: =IF(B12="","",ROW()-4) | G12: =IF(B12="","","UNPAID")
A13: =IF(B13="","",ROW()-4) | G13: =IF(B13="","","UNPAID")
A14: =IF(B14="","",ROW()-4) | G14: =IF(B14="","","UNPAID")
A15: =IF(B15="","",ROW()-4) | G15: =IF(B15="","","UNPAID")
A16: =IF(B16="","",ROW()-4) | G16: =IF(B16="","","UNPAID")
A17: =IF(B17="","",ROW()-4) | G17: =IF(B17="","","UNPAID")
A18: =IF(B18="","",ROW()-4) | G18: =IF(B18="","","UNPAID")
... A502: =IF(B502="","",ROW()-4) | G502: =IF(B502="","","UNPAID")

Sheet MEMBER PAYMENT LEDGER (ಸದಸ್ಯರ ಪ
A1: MEMBER PAYMENT LEDGER (ಸದಸ್ಯರ ಪಾವತಿ ವಿವರ)
A2: Enter one row per member per month (ಪ್ರತಿ ಸದಸ್ಯರಿಗೆ ಪ್ರತಿ ತಿಂಗಳಿಗೆ ಒಂದು ಸಾಲು ನಮೂದಿಸಿ). Amount Paid should record actual money received, including any interest repayment received (ಬಡ್ಡಿ ಸೇರಿ ನಿಜವಾಗಿ ಬಂದ ಮೊತ್ತವನ್ನು ದಾಖಲಿಸಿ).
A4: SL No (ಕ್ರಮ ಸಂಖ್ಯೆ) | B4: Date (ದಿನಾಂಕ) | C4: Member Name (ಸದಸ್ಯರ ಹೆಸರು) | D4: Amount Paid (₹) (ಪಾವತಿಸಿದ ಮೊತ್ತ) | E4: Outstanding (₹) (ಬಾಕಿ ಮೊತ್ತ) | F4: Payment Status (ಪಾವತಿ ಸ್ಥಿತಿ) | G4: Payment Date (ಪಾವತಿ ದಿನಾಂಕ) | H4: Notes (ಟಿಪ್ಪಣಿಗಳು)
E5: =IF(C5="","",MAX(0,SUMIFS('CHIT REGISTER (ಮಾಸಿಕ ಚಿಟ್ ನೋಂದಣ'!$D$5:$D$502,'CHIT REGISTER (ಮಾಸಿಕ ಚಿಟ್ ನೋಂದಣ'!$F$5:$F$502,C5,'CHIT REGISTER (ಮಾಸಿಕ ಚಿಟ್ ನೋಂದಣ'!$G$5:$G$502,"UNPAID")-IF(F5="PAID",N(D5),0)))
E6: =IF(C6="","",MAX(0,SUMIFS('CHIT REGISTER (ಮಾಸಿಕ ಚಿಟ್ ನೋಂದಣ'!$D$5:$D$502,'CHIT REGISTER (ಮಾಸಿಕ ಚಿಟ್ ನೋಂದಣ'!$F$5:$F$502,C6,'CHIT REGISTER (ಮಾಸಿಕ ಚಿಟ್ ನೋಂದಣ'!$G$5:$G$502,"UNPAID")-IF(F6="PAID",N(D6),0)))
E7: =IF(C7="","",MAX(0,SUMIFS('CHIT REGISTER (ಮಾಸಿಕ ಚಿಟ್ ನೋಂದಣ'!$D$5:$D$502,'CHIT REGISTER (ಮಾಸಿಕ ಚಿಟ್ ನೋಂದಣ'!$F$5:$F$502,C7,'CHIT REGISTER (ಮಾಸಿಕ ಚಿಟ್ ನೋಂದಣ'!$G$5:$G$502,"UNPAID")-IF(F7="PAID",N(D7),0)))
E8: =IF(C8="","",MAX(0,SUMIFS('CHIT REGISTER (ಮಾಸಿಕ ಚಿಟ್ ನೋಂದಣ'!$D$5:$D$502,'CHIT REGISTER (ಮಾಸಿಕ ಚಿಟ್ ನೋಂದಣ'!$F$5:$F$502,C8,'CHIT REGISTER (ಮಾಸಿಕ ಚಿಟ್ ನೋಂದಣ'!$G$5:$G$502,"UNPAID")-IF(F8="PAID",N(D8),0)))
E9: =IF(C9="","",MAX(0,SUMIFS('CHIT REGISTER (ಮಾಸಿಕ ಚಿಟ್ ನೋಂದಣ'!$D$5:$D$502,'CHIT REGISTER (ಮಾಸಿಕ ಚಿಟ್ ನೋಂದಣ'!$F$5:$F$502,C9,'CHIT REGISTER (ಮಾಸಿಕ ಚಿಟ್ ನೋಂದಣ'!$G$5:$G$502,"UNPAID")-IF(F9="PAID",N(D9),0)))
E10: =IF(C10="","",MAX(0,SUMIFS('CHIT REGISTER (ಮಾಸಿಕ ಚಿಟ್ ನೋಂದಣ'!$D$5:$D$502,'CHIT REGISTER (ಮಾಸಿಕ ಚಿಟ್ ನೋಂದಣ'!$F$5:$F$502,C10,'CHIT REGISTER (ಮಾಸಿಕ ಚಿಟ್ ನೋಂದಣ'!$G$5:$G$502,"UNPAID")-IF(F10="PAID",N(D10),0)))
E11: =IF(C11="","",MAX(0,SUMIFS('CHIT REGISTER (ಮಾಸಿಕ ಚಿಟ್ ನೋಂದಣ'!$D$5:$D$502,'CHIT REGISTER (ಮಾಸಿಕ ಚಿಟ್ ನೋಂದಣ'!$F$5:$F$502,C11,'CHIT REGISTER (ಮಾಸಿಕ ಚಿಟ್ ನೋಂದಣ'!$G$5:$G$502,"UNPAID")-IF(F11="PAID",N(D11),0)))
E12: =IF(C12="","",MAX(0,SUMIFS('CHIT REGISTER (ಮಾಸಿಕ ಚಿಟ್ ನೋಂದಣ'!$D$5:$D$502,'CHIT REGISTER (ಮಾಸಿಕ ಚಿಟ್ ನೋಂದಣ'!$F$5:$F$502,C12,'CHIT REGISTER (ಮಾಸಿಕ ಚಿಟ್ ನೋಂದಣ'!$G$5:$G$502,"UNPAID")-IF(F12="PAID",N(D12),0)))
E13: =IF(C13="","",MAX(0,SUMIFS('CHIT REGISTER (ಮಾಸಿಕ ಚಿಟ್ ನೋಂದಣ'!$D$5:$D$502,'CHIT REGISTER (ಮಾಸಿಕ ಚಿಟ್ ನೋಂದಣ'!$F$5:$F$502,C13,'CHIT REGISTER (ಮಾಸಿಕ ಚಿಟ್ ನೋಂದಣ'!$G$5:$G$502,"UNPAID")-IF(F13="PAID",N(D13),0)))
E14: =IF(C14="","",MAX(0,SUMIFS('CHIT REGISTER (ಮಾಸಿಕ ಚಿಟ್ ನೋಂದಣ'!$D$5:$D$502,'CHIT REGISTER (ಮಾಸಿಕ ಚಿಟ್ ನೋಂದಣ'!$F$5:$F$502,C14,'CHIT REGISTER (ಮಾಸಿಕ ಚಿಟ್ ನೋಂದಣ'!$G$5:$G$502,"UNPAID")-IF(F14="PAID",N(D14),0)))
E15: =IF(C15="","",MAX(0,SUMIFS('CHIT REGISTER (ಮಾಸಿಕ ಚಿಟ್ ನೋಂದಣ'!$D$5:$D$502,'CHIT REGISTER (ಮಾಸಿಕ ಚಿಟ್ ನೋಂದಣ'!$F$5:$F$502,C15,'CHIT REGISTER (ಮಾಸಿಕ ಚಿಟ್ ನೋಂದಣ'!$G$5:$G$502,"UNPAID")-IF(F15="PAID",N(D15),0)))
E16: =IF(C16="","",MAX(0,SUMIFS('CHIT REGISTER (ಮಾಸಿಕ ಚಿಟ್ ನೋಂದಣ'!$D$5:$D$502,'CHIT REGISTER (ಮಾಸಿಕ ಚಿಟ್ ನೋಂದಣ'!$F$5:$F$502,C16,'CHIT REGISTER (ಮಾಸಿಕ ಚಿಟ್ ನೋಂದಣ'!$G$5:$G$502,"UNPAID")-IF(F16="PAID",N(D16),0)))
... E997: =IF(C997="","",MAX(0,SUMIFS('CHIT REGISTER (ಮಾಸಿಕ ಚಿಟ್ ನೋಂದಣ'!$D$5:$D$502,'CHIT REGISTER (ಮಾಸಿಕ ಚಿಟ್ ನೋಂದಣ'!$F$5:$F$502,C997,'CHIT REGISTER (ಮಾಸಿಕ ಚಿಟ್ ನೋಂದಣ'!$G$5:$G$502,"UNPAID")-IF(F997="PAID",N(D997),0)))
